{
	"backtraceGraph" : 
	{
		"commands" : 
		[
			"INSTALL"
		],
		"files" : 
		[
			"generated/CMakeLists.txt"
		],
		"nodes" : 
		[
			{
				"file" : 0
			},
			{
				"command" : 0,
				"file" : 0,
				"line" : 59,
				"parent" : 0
			}
		]
	},
	"installers" : 
	[
		{
			"backtrace" : 1,
			"component" : "Unspecified",
			"destination" : "/home/robocomp/robocomp/bin",
			"paths" : 
			[
				"bin/chocachoca"
			],
			"type" : "file"
		}
	],
	"paths" : 
	{
		"build" : "generated",
		"source" : "generated"
	}
}
